gorimboptim/BaseOptimizer.py
gorimboptim/LineSearch.py
gorimboptim/__init__.py
gorimboptim/magic_lib.py
mlnd_pkg_test-0.0.1.dist-info/LICENSE
mlnd_pkg_test-0.0.1.dist-info/METADATA
mlnd_pkg_test-0.0.1.dist-info/WHEEL
mlnd_pkg_test-0.0.1.dist-info/top_level.txt
mlnd_pkg_test-0.0.1.dist-info/RECORD
